seaworthy/__init__.py
seaworthy/checks.py
seaworthy/client.py
seaworthy/definitions.py
seaworthy/helpers.py
seaworthy/ps.py
seaworthy/testtools.py
seaworthy/utils.py
seaworthy/containers/__init__.py
seaworthy/containers/nginx.py
seaworthy/containers/postgresql.py
seaworthy/containers/rabbitmq.py
seaworthy/containers/redis.py
seaworthy/pytest/__init__.py
seaworthy/pytest/checks.py
seaworthy/pytest/fixtures.py
seaworthy/stream/__init__.py
seaworthy/stream/_timeout.py
seaworthy/stream/logs.py
seaworthy/stream/matchers.py
seaworthy/tests-core/__init__.py
seaworthy/tests-core/test_client.py
seaworthy/tests-core/test_definitions.py
seaworthy/tests-core/test_helpers.py
seaworthy/tests-core/test_ps.py
seaworthy/tests-core/test_utils.py
seaworthy/tests-core/stream/__init__.py
seaworthy/tests-core/stream/fake_stream.py
seaworthy/tests-core/stream/test_logs.py
seaworthy/tests-core/stream/test_matchers.py
seaworthy/tests-pytest/__init__.py
seaworthy/tests-pytest/test_fixtures.py
seaworthy/tests-pytest/test_fixtures_pytester.py
seaworthy/tests-testtools/__init__.py
seaworthy/tests-testtools/test_testtools.py
seaworthy-0.4.2.dist-info/LICENSE
seaworthy-0.4.2.dist-info/METADATA
seaworthy-0.4.2.dist-info/WHEEL
seaworthy-0.4.2.dist-info/entry_points.txt
seaworthy-0.4.2.dist-info/top_level.txt
seaworthy-0.4.2.dist-info/RECORD
