Metadata-Version: 2.1
Name: seaworthy
Version: 0.4.2
Summary: Test Docker container images
Home-page: https://github.com/praekeltfoundation/seaworthy
Author: Praekelt.org SRE team
Author-email: sre@praekelt.org
License: BSD
Platform: UNKNOWN
Classifier: Development Status :: 4 - Beta
Classifier: Framework :: Pytest
Classifier: License :: OSI Approved :: BSD License
Classifier: Natural Language :: English
Classifier: Operating System :: POSIX :: Linux
Classifier: Programming Language :: Python :: 3 :: Only
Classifier: Programming Language :: Python :: 3.4
Classifier: Programming Language :: Python :: 3.5
Classifier: Programming Language :: Python :: 3.6
Classifier: Programming Language :: Python :: 3.7
Classifier: Programming Language :: Python :: 3
Classifier: Topic :: Software Development :: Libraries :: Python Modules
Classifier: Topic :: Software Development :: Testing
Requires-Dist: attrs (>=17.4.0)
Requires-Dist: docker (<4,>=3.6)
Requires-Dist: hyperlink
Requires-Dist: requests
Provides-Extra: docstest
Requires-Dist: doc8 ; extra == 'docstest'
Requires-Dist: readme-renderer ; extra == 'docstest'
Requires-Dist: Sphinx (<1.8,>=1.7) ; extra == 'docstest'
Requires-Dist: sphinx-rtd-theme ; extra == 'docstest'
Provides-Extra: pep8test
Requires-Dist: flake8 (>=3.7.0) ; extra == 'pep8test'
Requires-Dist: flake8-import-order ; extra == 'pep8test'
Requires-Dist: pep8-naming ; extra == 'pep8test'
Provides-Extra: pytest
Requires-Dist: pytest (>=3.0.0) ; extra == 'pytest'
Provides-Extra: test
Requires-Dist: pytest (>=3.0.0) ; extra == 'test'
Requires-Dist: responses ; extra == 'test'
Requires-Dist: testtools ; extra == 'test'
Provides-Extra: test-core
Requires-Dist: responses ; extra == 'test-core'
Provides-Extra: testtools
Requires-Dist: testtools ; extra == 'testtools'
